[
  {
    "name": "Taverley Underground",
    "areaId": "area.taverley_dungeon",
    "levels": [
      0,
      1,
      2,
      3
    ],
    "polygons": [
      {
        "vertices": [
          {
            "x": 2752,
            "z": 9792
          },
          {
            "x": 2816,
            "z": 9792
          },
          {
            "x": 2816,
            "z": 9856
          },
          {
            "x": 2816,
            "z": 9833
          },
          {
            "x": 2814,
            "z": 9832
          },
          {
            "x": 2814,
            "z": 9825
          },
          {
            "x": 2816,
            "z": 9823
          },
          {
            "x": 2816,
            "z": 9728
          },
          {
            "x": 2880,
            "z": 9728
          },
          {
            "x": 2880,
            "z": 9664
          },
          {
            "x": 2944,
            "z": 9664
          },
          {
            "x": 2944,
            "z": 9728
          },
          {
            "x": 2944,
            "z": 9765
          },
          {
            "x": 2973,
            "z": 9765
          },
          {
            "x": 2973,
            "z": 9800
          },
          {
            "x": 2952,
            "z": 9800
          },
          {
            "x": 2944,
            "z": 9805
          },
          {
            "x": 2944,
            "z": 9856
          },
          {
            "x": 2752,
            "z": 9856
          }
        ]
      },
      {
        "vertices": [
          {
            "x": 2752,
            "z": 9664
          },
          {
            "x": 3007,
            "z": 9664
          },
          {
            "x": 3007,
            "z": 9855
          },
          {
            "x": 2752,
            "z": 9855
          }
        ]
      }
    ]
  }
]
